ride_the_duck/__init__.py
ride_the_duck/__main__.py
ride_the_duck/_version.py
ride_the_duck/mainGame.py
ride_the_duck-1.0.31.dist-info/licenses/LICENSE
ride_the_duck-1.0.31.dist-info/METADATA
ride_the_duck-1.0.31.dist-info/WHEEL
ride_the_duck-1.0.31.dist-info/entry_points.txt
ride_the_duck-1.0.31.dist-info/top_level.txt
ride_the_duck-1.0.31.dist-info/RECORD
