Metadata-Version: 2.4
Name: ride-the-duck
Version: 1.0.31
Summary: A terminal-based gambling card game inspired by 'Ride The Bus'
Author-email: Braeden Sy Tan <braedenjairsytan@icloud.com>
License: MIT
Project-URL: Homepage, https://github.com/DuckyBoi-XD/Ride-The-Duck
Project-URL: Repository, https://github.com/DuckyBoi-XD/Ride-The-Duck
Project-URL: Issues, https://github.com/DuckyBoi-XD/Ride-The-Duck/issues
Keywords: game,cards,gambling,terminal
Classifier: Development Status :: 4 - Beta
Classifier: Intended Audience :: End Users/Desktop
Classifier: Topic :: Games/Entertainment :: Arcade
Classifier: Programming Language :: Python :: 3
Requires-Python: >=3.8
License-File: LICENSE
Dynamic: license-file
